[
  {
    "代碼": 1,
    "學校名稱": "國立臺灣大學",
    "址址": "臺北市大安區羅斯福路四段1號",
    "郵遞區號": 106319,
    "學校簡稱": "臺大",
    "學業成績百分比": 20,
    "不分學群可選填志願數": NaN,
    "一類學群可選填志願數": 12.0,
    "二類學群可選填志願數": 9.0,
    "三類學群可選填志願數": 10.0,
    "四類學群可選填志願數": NaN,
    "五類學群可選填志願數": NaN,
    "六類學群可選填志願數": NaN,
    "七類學群可選填志願數": NaN,
    "八類學群可選填志願數": 1.0,
    "外加名額不分學群可選填志願數": NaN,
    "外加名額第一類學群可選填志願數": 3.0,
    "外加名額第二類學群可選填志願數": 1.0,
    "外加名額第三類學群可選填志願數": 2.0,
    "外加名額第四類學群可選填志願數": NaN,
    "外加名額第五類學群可選填志願數": NaN,
    "外加名額第六類學群可選填志願數": NaN,
    "外加名額第七類學群可選填志願數": NaN,
    "外加名額第八類學群可選填志願數": NaN
  },
  {
    "代碼": 2,
    "學校名稱": "國立臺灣師範大學",
    "址址": "臺北市大安區和平東路一段162號",
    "郵遞區號": 106,
    "學校簡稱": "師大",
    "學業成績百分比": 20,
    "不分學群可選填志願數": NaN,
    "一類學群可選填志願數": 9.0,
    "二類學群可選填志願數": 8.0,
    "三類學群可選填志願數": 2.0,
    "四類學群可選填志願數": NaN,
    "五類學群可選填志願數": 2.0,
    "六類學群可選填志願數": NaN,
    "七類學群可選填志願數": 1.0,
    "八類學群可選填志願數": NaN,
    "外加名額不分學群可選填志願數": NaN,
    "外加名額第一類學群可選填志願數": 9.0,
    "外加名額第二類學群可選填志願數": 4.0,
    "外加名額第三類學群可選填志願數": 2.0,
    "外加名額第四類學群可選填志願數": NaN,
    "外加名額第五類學群可選填志願數": NaN,
    "外加名額第六類學群可選填志願數": NaN,
    "外加名額第七類學群可選填志願數": NaN,
    "外加名額第八類學群可選填志願數": NaN
  },
  {
    "代碼": 3,
    "學校名稱": "國立中興大學",
    "址址": "臺中市南區興大路145號",
    "郵遞區號": 402202,
    "學校簡稱": "中興",
    "學業成績百分比": 30,
    "不分學群可選填志願數": NaN,
    "一類學群可選填志願數": 10.0,
    "二類學群可選填志願數": 17.0,
    "三類學群可選填志願數": 14.0,
    "四類學群可選填志願數": NaN,
    "五類學群可選填志願數": NaN,
    "六類學群可選填志願數": NaN,
    "七類學群可選填志願數": NaN,
    "八類學群可選填志願數": NaN,
    "外加名額不分學群可選填志願數": NaN,
    "外加名額第一類學群可選填志願數": 10.0,
    "外加名額第二類學群可選填志願數": 15.0,
    "外加名額第三類學群可選填志願數": 13.0,
    "外加名額第四類學群可選填志願數": NaN,
    "外加名額第五類學群可選填志願數": NaN,
    "外加名額第六類學群可選填志願數": NaN,
    "外加名額第七類學群可選填志願數": NaN,
    "外加名額第八類學群可選填志願數": NaN
  },
  {
    "代碼": 4,
    "學校名稱": "國立成功大學",
    "址址": "台南市東區大學路1號",
    "郵遞區號": 701,
    "學校簡稱": "成大",
    "學業成績百分比": 20,
    "不分學群可選填志願數": NaN,
    "一類學群可選填志願數": 5.0,
    "二類學群可選填志願數": 14.0,
    "三類學群可選填志願數": 4.0,
    "四類學群可選填志願數": NaN,
    "五類學群可選填志願數": NaN,
    "六類學群可選填志願數": NaN,
    "七類學群可選填志願數": NaN,
    "八類學群可選填志願數": 1.0,
    "外加名額不分學群可選填志願數": NaN,
    "外加名額第一類學群可選填志願數": 2.0,
    "外加名額第二類學群可選填志願數": 6.0,
    "外加名額第三類學群可選填志願數": 2.0,
    "外加名額第四類學群可選填志願數": NaN,
    "外加名額第五類學群可選填志願數": NaN,
    "外加名額第六類學群可選填志願數": NaN,
    "外加名額第七類學群可選填志願數": NaN,
    "外加名額第八類學群可選填志願數": NaN
  },
  {
    "代碼": 5,
    "學校名稱": "東吳大學",
    "址址": "臺北市士林區臨溪路70號",
    "郵遞區號": 111002,
    "學校簡稱": "東吳",
    "學業成績百分比": 50,
    "不分學群可選填志願數": NaN,
    "一類學群可選填志願數": 18.0,
    "二類學群可選填志願數": 3.0,
    "三類學群可選填志願數": 2.0,
    "四類學群可選填志願數": NaN,
    "五類學群可選填志願數": NaN,
    "六類學群可選填志願數": NaN,
    "七類學群可選填志願數": NaN,
    "八類學群可選填志願數": NaN,
    "外加名額不分學群可選填志願數": NaN,
    "外加名額第一類學群可選填志願數": 11.0,
    "外加名額第二類學群可選填志願數": 2.0,
    "外加名額第三類學群可選填志願數": 1.0,
    "外加名額第四類學群可選填志願數": NaN,
    "外加名額第五類學群可選填志願數": NaN,
    "外加名額第六類學群可選填志願數": NaN,
    "外加名額第七類學群可選填志願數": NaN,
    "外加名額第八類學群可選填志願數": NaN
  },
  {
    "代碼": 6,
    "學校名稱": "國立政治大學",
    "址址": "臺北市文山區指南路二段64號",
    "郵遞區號": 116011,
    "學校簡稱": "政大",
    "學業成績百分比": 20,
    "不分學群可選填志願數": NaN,
    "一類學群可選填志願數": 18.0,
    "二類學群可選填志願數": 5.0,
    "三類學群可選填志願數": NaN,
    "四類學群可選填志願數": NaN,
    "五類學群可選填志願數": NaN,
    "六類學群可選填志願數": NaN,
    "七類學群可選填志願數": NaN,
    "八類學群可選填志願數": NaN,
    "外加名額不分學群可選填志願數": NaN,
    "外加名額第一類學群可選填志願數": 11.0,
    "外加名額第二類學群可選填志願數": 2.0,
    "外加名額第三類學群可選填志願數": NaN,
    "外加名額第四類學群可選填志願數": NaN,
    "外加名額第五類學群可選填志願數": NaN,
    "外加名額第六類學群可選填志願數": NaN,
    "外加名額第七類學群可選填志願數": NaN,
    "外加名額第八類學群可選填志願數": NaN
  },
  {
    "代碼": 7,
    "學校名稱": "高雄醫學大學",
    "址址": "高雄市三民區十全一路100號",
    "郵遞區號": 807,
    "學校簡稱": "高醫",
    "學業成績百分比": 40,
    "不分學群可選填志願數": NaN,
    "一類學群可選填志願數": 2.0,
    "二類學群可選填志願數": 4.0,
    "三類學群可選填志願數": 8.0,
    "四類學群可選填志願數": NaN,
    "五類學群可選填志願數": NaN,
    "六類學群可選填志願數": NaN,
    "七類學群可選填志願數": NaN,
    "八類學群可選填志願數": 1.0,
    "外加名額不分學群可選填志願數": NaN,
    "外加名額第一類學群可選填志願數": 1.0,
    "外加名額第二類學群可選填志願數": 3.0,
    "外加名額第三類學群可選填志願數": 8.0,
    "外加名額第四類學群可選填志願數": NaN,
    "外加名額第五類學群可選填志願數": NaN,
    "外加名額第六類學群可選填志願數": NaN,
    "外加名額第七類學群可選填志願數": NaN,
    "外加名額第八類學群可選填志願數": NaN
  },
  {
    "代碼": 8,
    "學校名稱": "中原大學",
    "址址": "桃園市中壢區中北路200號",
    "郵遞區號": 320314,
    "學校簡稱": "中原",
    "學業成績百分比": 50,
    "不分學群可選填志願數": NaN,
    "一類學群可選填志願數": 15.0,
    "二類學群可選填志願數": 22.0,
    "三類學群可選填志願數": 2.0,
    "四類學群可選填志願數": NaN,
    "五類學群可選填志願數": 2.0,
    "六類學群可選填志願數": NaN,
    "七類學群可選填志願數": NaN,
    "八類學群可選填志願數": NaN,
    "外加名額不分學群可選填志願數": NaN,
    "外加名額第一類學群可選填志願數": 6.0,
    "外加名額第二類學群可選填志願數": 11.0,
    "外加名額第三類學群可選填志願數": 2.0,
    "外加名額第四類學群可選填志願數": NaN,
    "外加名額第五類學群可選填志願數": NaN,
    "外加名額第六類學群可選填志願數": NaN,
    "外加名額第七類學群可選填志願數": NaN,
    "外加名額第八類學群可選填志願數": NaN
  },
  {
    "代碼": 9,
    "學校名稱": "東海大學",
    "址址": "台中市西屯區臺灣大道四段1727號",
    "郵遞區號": 407224,
    "學校簡稱": "東海",
    "學業成績百分比": 50,
    "不分學群可選填志願數": NaN,
    "一類學群可選填志願數": 21.0,
    "二類學群可選填志願數": 15.0,
    "三類學群可選填志願數": 5.0,
    "四類學群可選填志願數": NaN,
    "五類學群可選填志願數": 1.0,
    "六類學群可選填志願數": NaN,
    "七類學群可選填志願數": NaN,
    "八類學群可選填志願數": NaN,
    "外加名額不分學群可選填志願數": NaN,
    "外加名額第一類學群可選填志願數": 15.0,
    "外加名額第二類學群可選填志願數": 14.0,
    "外加名額第三類學群可選填志願數": 5.0,
    "外加名額第四類學群可選填志願數": NaN,
    "外加名額第五類學群可選填志願數": NaN,
    "外加名額第六類學群可選填志願數": NaN,
    "外加名額第七類學群可選填志願數": NaN,
    "外加名額第八類學群可選填志願數": NaN
  },
  {
    "代碼": 11,
    "學校名稱": "國立清華大學",
    "址址": "新竹市光復路二段101號",
    "郵遞區號": 300044,
    "學校簡稱": "清大",
    "學業成績百分比": 20,
    "不分學群可選填志願數": NaN,
    "一類學群可選填志願數": 13.0,
    "二類學群可選填志願數": 21.0,
    "三類學群可選填志願數": 3.0,
    "四類學群可選填志願數": NaN,
    "五類學群可選填志願數": 2.0,
    "六類學群可選填志願數": NaN,
    "七類學群可選填志願數": NaN,
    "八類學群可選填志願數": NaN,
    "外加名額不分學群可選填志願數": NaN,
    "外加名額第一類學群可選填志願數": 9.0,
    "外加名額第二類學群可選填志願數": 11.0,
    "外加名額第三類學群可選填志願數": NaN,
    "外加名額第四類學群可選填志願數": NaN,
    "外加名額第五類學群可選填志願數": NaN,
    "外加名額第六類學群可選填志願數": NaN,
    "外加名額第七類學群可選填志願數": NaN,
    "外加名額第八類學群可選填志願數": NaN
  },
  {
    "代碼": 12,
    "學校名稱": "中國醫藥大學",
    "址址": "臺中市北屯區經貿路一段100號",
    "郵遞區號": 406040,
    "學校簡稱": "中國醫",
    "學業成績百分比": 50,
    "不分學群可選填志願數": NaN,
    "一類學群可選填志願數": NaN,
    "二類學群可選填志願數": NaN,
    "三類學群可選填志願數": 15.0,
    "四類學群可選填志願數": NaN,
    "五類學群可選填志願數": NaN,
    "六類學群可選填志願數": NaN,
    "七類學群可選填志願數": NaN,
    "八類學群可選填志願數": 2.0,
    "外加名額不分學群可選填志願數": NaN,
    "外加名額第一類學群可選填志願數": NaN,
    "外加名額第二類學群可選填志願數": NaN,
    "外加名額第三類學群可選填志願數": 13.0,
    "外加名額第四類學群可選填志願數": NaN,
    "外加名額第五類學群可選填志願數": NaN,
    "外加名額第六類學群可選填志願數": NaN,
    "外加名額第七類學群可選填志願數": NaN,
    "外加名額第八類學群可選填志願數": NaN
  },
  {
    "代碼": 13,
    "學校名稱": "國立陽明交通大學",
    "址址": "新竹市大學路1001號",
    "郵遞區號": 300,
    "學校簡稱": "陽明交通",
    "學業成績百分比": 20,
    "不分學群可選填志願數": NaN,
    "一類學群可選填志願數": 5.0,
    "二類學群可選填志願數": 20.0,
    "三類學群可選填志願數": 5.0,
    "四類學群可選填志願數": NaN,
    "五類學群可選填志願數": NaN,
    "六類學群可選填志願數": NaN,
    "七類學群可選填志願數": NaN,
    "八類學群可選填志願數": 1.0,
    "外加名額不分學群可選填志願數": NaN,
    "外加名額第一類學群可選填志願數": 4.0,
    "外加名額第二類學群可選填志願數": 4.0,
    "外加名額第三類學群可選填志願數": 1.0,
    "外加名額第四類學群可選填志願數": NaN,
    "外加名額第五類學群可選填志願數": NaN,
    "外加名額第六類學群可選填志願數": NaN,
    "外加名額第七類學群可選填志願數": NaN,
    "外加名額第八類學群可選填志願數": NaN
  },
  {
    "代碼": 14,
    "學校名稱": "淡江大學",
    "址址": "新北市淡水區英專路151號",
    "郵遞區號": 251301,
    "學校簡稱": "淡江",
    "學業成績百分比": 50,
    "不分學群可選填志願數": NaN,
    "一類學群可選填志願數": 31.0,
    "二類學群可選填志願數": 14.0,
    "三類學群可選填志願數": NaN,
    "四類學群可選填志願數": NaN,
    "五類學群可選填志願數": NaN,
    "六類學群可選填志願數": NaN,
    "七類學群可選填志願數": NaN,
    "八類學群可選填志願數": NaN,
    "外加名額不分學群可選填志願數": NaN,
    "外加名額第一類學群可選填志願數": 27.0,
    "外加名額第二類學群可選填志願數": 13.0,
    "外加名額第三類學群可選填志願數": NaN,
    "外加名額第四類學群可選填志願數": NaN,
    "外加名額第五類學群可選填志願數": NaN,
    "外加名額第六類學群可選填志願數": NaN,
    "外加名額第七類學群可選填志願數": NaN,
    "外加名額第八類學群可選填志願數": NaN
  },
  {
    "代碼": 15,
    "學校名稱": "逢甲大學",
    "址址": "臺中市西屯區文華路100號",
    "郵遞區號": 407102,
    "學校簡稱": "逢甲",
    "學業成績百分比": 50,
    "不分學群可選填志願數": NaN,
    "一類學群可選填志願數": 24.0,
    "二類學群可選填志願數": 26.0,
    "三類學群可選填志願數": NaN,
    "四類學群可選填志願數": NaN,
    "五類學群可選填志願數": NaN,
    "六類學群可選填志願數": NaN,
    "七類學群可選填志願數": NaN,
    "八類學群可選填志願數": NaN,
    "外加名額不分學群可選填志願數": NaN,
    "外加名額第一類學群可選填志願數": 20.0,
    "外加名額第二類學群可選填志願數": 20.0,
    "外加名額第三類學群可選填志願數": NaN,
    "外加名額第四類學群可選填志願數": NaN,
    "外加名額第五類學群可選填志願數": NaN,
    "外加名額第六類學群可選填志願數": NaN,
    "外加名額第七類學群可選填志願數": NaN,
    "外加名額第八類學群可選填志願數": NaN
  },
  {
    "代碼": 16,
    "學校名稱": "國立中央大學",
    "址址": "桃園市中壢區中大路300號",
    "郵遞區號": 320,
    "學校簡稱": "中央",
    "學業成績百分比": 20,
    "不分學群可選填志願數": NaN,
    "一類學群可選填志願數": 10.0,
    "二類學群可選填志願數": 23.0,
    "三類學群可選填志願數": 1.0,
    "四類學群可選填志願數": NaN,
    "五類學群可選填志願數": NaN,
    "六類學群可選填志願數": NaN,
    "七類學群可選填志願數": NaN,
    "八類學群可選填志願數": NaN,
    "外加名額不分學群可選填志願數": NaN,
    "外加名額第一類學群可選填志願數": 10.0,
    "外加名額第二類學群可選填志願數": 22.0,
    "外加名額第三類學群可選填志願數": 1.0,
    "外加名額第四類學群可選填志願數": NaN,
    "外加名額第五類學群可選填志願數": NaN,
    "外加名額第六類學群可選填志願數": NaN,
    "外加名額第七類學群可選填志願數": NaN,
    "外加名額第八類學群可選填志願數": NaN
  },
  {
    "代碼": 17,
    "學校名稱": "中國文化大學",
    "址址": "臺北市士林區華岡路55號",
    "郵遞區號": 111396,
    "學校簡稱": "文化",
    "學業成績百分比": 50,
    "不分學群可選填志願數": NaN,
    "一類學群可選填志願數": 30.0,
    "二類學群可選填志願數": 12.0,
    "三類學群可選填志願數": 7.0,
    "四類學群可選填志願數": NaN,
    "五類學群可選填志願數": NaN,
    "六類學群可選填志願數": NaN,
    "七類學群可選填志願數": NaN,
    "八類學群可選填志願數": NaN,
    "外加名額不分學群可選填志願數": NaN,
    "外加名額第一類學群可選填志願數": 26.0,
    "外加名額第二類學群可選填志願數": 12.0,
    "外加名額第三類學群可選填志願數": 7.0,
    "外加名額第四類學群可選填志願數": NaN,
    "外加名額第五類學群可選填志願數": NaN,
    "外加名額第六類學群可選填志願數": NaN,
    "外加名額第七類學群可選填志願數": NaN,
    "外加名額第八類學群可選填志願數": NaN
  },
  {
    "代碼": 18,
    "學校名稱": "靜宜大學",
    "址址": "臺中市沙鹿區臺灣大道七段200號",
    "郵遞區號": 433303,
    "學校簡稱": "靜宜",
    "學業成績百分比": 50,
    "不分學群可選填志願數": NaN,
    "一類學群可選填志願數": 18.0,
    "二類學群可選填志願數": 8.0,
    "三類學群可選填志願數": 1.0,
    "四類學群可選填志願數": NaN,
    "五類學群可選填志願數": NaN,
    "六類學群可選填志願數": NaN,
    "七類學群可選填志願數": NaN,
    "八類學群可選填志願數": NaN,
    "外加名額不分學群可選填志願數": NaN,
    "外加名額第一類學群可選填志願數": 18.0,
    "外加名額第二類學群可選填志願數": 8.0,
    "外加名額第三類學群可選填志願數": 1.0,
    "外加名額第四類學群可選填志願數": NaN,
    "外加名額第五類學群可選填志願數": NaN,
    "外加名額第六類學群可選填志願數": NaN,
    "外加名額第七類學群可選填志願數": NaN,
    "外加名額第八類學群可選填志願數": NaN
  },
  {
    "代碼": 19,
    "學校名稱": "大同大學",
    "址址": "臺北市中山區中山北路三段40號",
    "郵遞區號": 10452,
    "學校簡稱": "大同",
    "學業成績百分比": 50,
    "不分學群可選填志願數": NaN,
    "一類學群可選填志願數": 3.0,
    "二類學群可選填志願數": 5.0,
    "三類學群可選填志願數": 1.0,
    "四類學群可選填志願數": NaN,
    "五類學群可選填志願數": NaN,
    "六類學群可選填志願數": NaN,
    "七類學群可選填志願數": NaN,
    "八類學群可選填志願數": NaN,
    "外加名額不分學群可選填志願數": NaN,
    "外加名額第一類學群可選填志願數": 3.0,
    "外加名額第二類學群可選填志願數": 5.0,
    "外加名額第三類學群可選填志願數": 1.0,
    "外加名額第四類學群可選填志願數": NaN,
    "外加名額第五類學群可選填志願數": NaN,
    "外加名額第六類學群可選填志願數": NaN,
    "外加名額第七類學群可選填志願數": NaN,
    "外加名額第八類學群可選填志願數": NaN
  },
  {
    "代碼": 20,
    "學校名稱": "輔仁大學",
    "址址": "新北市新莊區中正路510號",
    "郵遞區號": 242062,
    "學校簡稱": "輔仁",
    "學業成績百分比": 50,
    "不分學群可選填志願數": NaN,
    "一類學群可選填志願數": 35.0,
    "二類學群可選填志願數": 9.0,
    "三類學群可選填志願數": 9.0,
    "四類學群可選填志願數": NaN,
    "五類學群可選填志願數": 1.0,
    "六類學群可選填志願數": NaN,
    "七類學群可選填志願數": NaN,
    "八類學群可選填志願數": 1.0,
    "外加名額不分學群可選填志願數": NaN,
    "外加名額第一類學群可選填志願數": 14.0,
    "外加名額第二類學群可選填志願數": 4.0,
    "外加名額第三類學群可選填志願數": 4.0,
    "外加名額第四類學群可選填志願數": NaN,
    "外加名額第五類學群可選填志願數": 1.0,
    "外加名額第六類學群可選填志願數": NaN,
    "外加名額第七類學群可選填志願數": NaN,
    "外加名額第八類學群可選填志願數": NaN
  },
  {
    "代碼": 21,
    "學校名稱": "國立臺灣海洋大學",
    "址址": "基隆市中正區北寧路2號",
    "郵遞區號": 202301,
    "學校簡稱": "海洋",
    "學業成績百分比": 40,
    "不分學群可選填志願數": NaN,
    "一類學群可選填志願數": 6.0,
    "二類學群可選填志願數": 12.0,
    "三類學群可選填志願數": 5.0,
    "四類學群可選填志願數": NaN,
    "五類學群可選填志願數": NaN,
    "六類學群可選填志願數": NaN,
    "七類學群可選填志願數": NaN,
    "八類學群可選填志願數": NaN,
    "外加名額不分學群可選填志願數": NaN,
    "外加名額第一類學群可選填志願數": 5.0,
    "外加名額第二類學群可選填志願數": 12.0,
    "外加名額第三類學群可選填志願數": 4.0,
    "外加名額第四類學群可選填志願數": NaN,
    "外加名額第五類學群可選填志願數": NaN,
    "外加名額第六類學群可選填志願數": NaN,
    "外加名額第七類學群可選填志願數": NaN,
    "外加名額第八類學群可選填志願數": NaN
  },
  {
    "代碼": 22,
    "學校名稱": "國立高雄師範大學",
    "址址": "高雄市苓雅區和平一路116號",
    "郵遞區號": 80201,
    "學校簡稱": "高師大",
    "學業成績百分比": 40,
    "不分學群可選填志願數": NaN,
    "一類學群可選填志願數": 7.0,
    "二類學群可選填志願數": 9.0,
    "三類學群可選填志願數": 1.0,
    "四類學群可選填志願數": NaN,
    "五類學群可選填志願數": 2.0,
    "六類學群可選填志願數": NaN,
    "七類學群可選填志願數": 1.0,
    "八類學群可選填志願數": NaN,
    "外加名額不分學群可選填志願數": NaN,
    "外加名額第一類學群可選填志願數": 7.0,
    "外加名額第二類學群可選填志願數": 8.0,
    "外加名額第三類學群可選填志願數": 1.0,
    "外加名額第四類學群可選填志願數": NaN,
    "外加名額第五類學群可選填志願數": 1.0,
    "外加名額第六類學群可選填志願數": NaN,
    "外加名額第七類學群可選填志願數": 1.0,
    "外加名額第八類學群可選填志願數": NaN
  },
  {
    "代碼": 23,
    "學校名稱": "國立彰化師範大學",
    "址址": "彰化市進德路1號",
    "郵遞區號": 500207,
    "學校簡稱": "彰師大",
    "學業成績百分比": 30,
    "不分學群可選填志願數": NaN,
    "一類學群可選填志願數": 12.0,
    "二類學群可選填志願數": 9.0,
    "三類學群可選填志願數": 1.0,
    "四類學群可選填志願數": NaN,
    "五類學群可選填志願數": 1.0,
    "六類學群可選填志願數": NaN,
    "七類學群可選填志願數": NaN,
    "八類學群可選填志願數": NaN,
    "外加名額不分學群可選填志願數": NaN,
    "外加名額第一類學群可選填志願數": 10.0,
    "外加名額第二類學群可選填志願數": 8.0,
    "外加名額第三類學群可選填志願數": 1.0,
    "外加名額第四類學群可選填志願數": NaN,
    "外加名額第五類學群可選填志願數": 1.0,
    "外加名額第六類學群可選填志願數": NaN,
    "外加名額第七類學群可選填志願數": NaN,
    "外加名額第八類學群可選填志願數": NaN
  },
  {
    "代碼": 26,
    "學校名稱": "中山醫學大學",
    "址址": "臺中市南區建國北路一段110號",
    "郵遞區號": 402,
    "學校簡稱": "中山醫",
    "學業成績百分比": 50,
    "不分學群可選填志願數": NaN,
    "一類學群可選填志願數": 3.0,
    "二類學群可選填志願數": 1.0,
    "三類學群可選填志願數": 16.0,
    "四類學群可選填志願數": NaN,
    "五類學群可選填志願數": NaN,
    "六類學群可選填志願數": NaN,
    "七類學群可選填志願數": NaN,
    "八類學群可選填志願數": 1.0,
    "外加名額不分學群可選填志願數": NaN,
    "外加名額第一類學群可選填志願數": 3.0,
    "外加名額第二類學群可選填志願數": 1.0,
    "外加名額第三類學群可選填志願數": 16.0,
    "外加名額第四類學群可選填志願數": NaN,
    "外加名額第五類學群可選填志願數": NaN,
    "外加名額第六類學群可選填志願數": NaN,
    "外加名額第七類學群可選填志願數": NaN,
    "外加名額第八類學群可選填志願數": NaN
  },
  {
    "代碼": 27,
    "學校名稱": "國立中山大學",
    "址址": "高雄市鼓山區蓮海路70號",
    "郵遞區號": 80424,
    "學校簡稱": "中山",
    "學業成績百分比": 20,
    "不分學群可選填志願數": NaN,
    "一類學群可選填志願數": 10.0,
    "二類學群可選填志願數": 16.0,
    "三類學群可選填志願數": 5.0,
    "四類學群可選填志願數": 1.0,
    "五類學群可選填志願數": NaN,
    "六類學群可選填志願數": NaN,
    "七類學群可選填志願數": NaN,
    "八類學群可選填志願數": NaN,
    "外加名額不分學群可選填志願數": NaN,
    "外加名額第一類學群可選填志願數": 3.0,
    "外加名額第二類學群可選填志願數": 8.0,
    "外加名額第三類學群可選填志願數": 3.0,
    "外加名額第四類學群可選填志願數": NaN,
    "外加名額第五類學群可選填志願數": NaN,
    "外加名額第六類學群可選填志願數": NaN,
    "外加名額第七類學群可選填志願數": NaN,
    "外加名額第八類學群可選填志願數": NaN
  },
  {
    "代碼": 28,
    "學校名稱": "國立臺北藝術大學",
    "址址": "臺北市北投區學園路1號",
    "郵遞區號": 112301,
    "學校簡稱": "北藝大",
    "學業成績百分比": 20,
    "不分學群可選填志願數": NaN,
    "一類學群可選填志願數": 3.0,
    "二類學群可選填志願數": 1.0,
    "三類學群可選填志願數": NaN,
    "四類學群可選填志願數": 1.0,
    "五類學群可選填志願數": 2.0,
    "六類學群可選填志願數": NaN,
    "七類學群可選填志願數": NaN,
    "八類學群可選填志願數": NaN,
    "外加名額不分學群可選填志願數": NaN,
    "外加名額第一類學群可選填志願數": 1.0,
    "外加名額第二類學群可選填志願數": NaN,
    "外加名額第三類學群可選填志願數": NaN,
    "外加名額第四類學群可選填志願數": 1.0,
    "外加名額第五類學群可選填志願數": NaN,
    "外加名額第六類學群可選填志願數": NaN,
    "外加名額第七類學群可選填志願數": NaN,
    "外加名額第八類學群可選填志願數": NaN
  },
  {
    "代碼": 30,
    "學校名稱": "長庚大學",
    "址址": "桃園市龜山區文化一路259號",
    "郵遞區號": 333,
    "學校簡稱": "長庚",
    "學業成績百分比": 30,
    "不分學群可選填志願數": NaN,
    "一類學群可選填志願數": 6.0,
    "二類學群可選填志願數": 8.0,
    "三類學群可選填志願數": 8.0,
    "四類學群可選填志願數": NaN,
    "五類學群可選填志願數": NaN,
    "六類學群可選填志願數": NaN,
    "七類學群可選填志願數": NaN,
    "八類學群可選填志願數": 1.0,
    "外加名額不分學群可選填志願數": NaN,
    "外加名額第一類學群可選填志願數": 4.0,
    "外加名額第二類學群可選填志願數": 1.0,
    "外加名額第三類學群可選填志願數": 1.0,
    "外加名額第四類學群可選填志願數": NaN,
    "外加名額第五類學群可選填志願數": NaN,
    "外加名額第六類學群可選填志願數": NaN,
    "外加名額第七類學群可選填志願數": NaN,
    "外加名額第八類學群可選填志願數": NaN
  },
  {
    "代碼": 31,
    "學校名稱": "國立臺中教育大學",
    "址址": "臺中市西區民生路140號",
    "郵遞區號": 403514,
    "學校簡稱": "中教",
    "學業成績百分比": 40,
    "不分學群可選填志願數": NaN,
    "一類學群可選填志願數": 11.0,
    "二類學群可選填志願數": 5.0,
    "三類學群可選填志願數": NaN,
    "四類學群可選填志願數": NaN,
    "五類學群可選填志願數": 1.0,
    "六類學群可選填志願數": NaN,
    "七類學群可選填志願數": NaN,
    "八類學群可選填志願數": NaN,
    "外加名額不分學群可選填志願數": NaN,
    "外加名額第一類學群可選填志願數": 11.0,
    "外加名額第二類學群可選填志願數": 5.0,
    "外加名額第三類學群可選填志願數": NaN,
    "外加名額第四類學群可選填志願數": NaN,
    "外加名額第五類學群可選填志願數": NaN,
    "外加名額第六類學群可選填志願數": NaN,
    "外加名額第七類學群可選填志願數": NaN,
    "外加名額第八類學群可選填志願數": NaN
  },
  {
    "代碼": 32,
    "學校名稱": "國立臺北教育大學",
    "址址": "臺北市大安區和平東路二段134號",
    "郵遞區號": 106320,
    "學校簡稱": "國北教",
    "學業成績百分比": 30,
    "不分學群可選填志願數": NaN,
    "一類學群可選填志願數": 11.0,
    "二類學群可選填志願數": 5.0,
    "三類學群可選填志願數": NaN,
    "四類學群可選填志願數": NaN,
    "五類學群可選填志願數": 1.0,
    "六類學群可選填志願數": NaN,
    "七類學群可選填志願數": 1.0,
    "八類學群可選填志願數": NaN,
    "外加名額不分學群可選填志願數": NaN,
    "外加名額第一類學群可選填志願數": 9.0,
    "外加名額第二類學群可選填志願數": 3.0,
    "外加名額第三類學群可選填志願數": NaN,
    "外加名額第四類學群可選填志願數": NaN,
    "外加名額第五類學群可選填志願數": 1.0,
    "外加名額第六類學群可選填志願數": NaN,
    "外加名額第七類學群可選填志願數": 1.0,
    "外加名額第八類學群可選填志願數": NaN
  },
  {
    "代碼": 33,
    "學校名稱": "國立臺南大學",
    "址址": "臺南市中西區樹林街二段33號",
    "郵遞區號": 700301,
    "學校簡稱": "南大",
    "學業成績百分比": 30,
    "不分學群可選填志願數": NaN,
    "一類學群可選填志願數": 10.0,
    "二類學群可選填志願數": 6.0,
    "三類學群可選填志願數": 2.0,
    "四類學群可選填志願數": NaN,
    "五類學群可選填志願數": NaN,
    "六類學群可選填志願數": NaN,
    "七類學群可選填志願數": 1.0,
    "八類學群可選填志願數": NaN,
    "外加名額不分學群可選填志願數": NaN,
    "外加名額第一類學群可選填志願數": 9.0,
    "外加名額第二類學群可選填志願數": 4.0,
    "外加名額第三類學群可選填志願數": 2.0,
    "外加名額第四類學群可選填志願數": NaN,
    "外加名額第五類學群可選填志願數": NaN,
    "外加名額第六類學群可選填志願數": NaN,
    "外加名額第七類學群可選填志願數": 1.0,
    "外加名額第八類學群可選填志願數": NaN
  },
  {
    "代碼": 34,
    "學校名稱": "國立東華大學",
    "址址": "花蓮縣壽豐鄉大學路二段1號",
    "郵遞區號": 974301,
    "學校簡稱": "東華",
    "學業成績百分比": 50,
    "不分學群可選填志願數": NaN,
    "一類學群可選填志願數": 30.0,
    "二類學群可選填志願數": 12.0,
    "三類學群可選填志願數": 2.0,
    "四類學群可選填志願數": NaN,
    "五類學群可選填志願數": NaN,
    "六類學群可選填志願數": NaN,
    "七類學群可選填志願數": 1.0,
    "八類學群可選填志願數": NaN,
    "外加名額不分學群可選填志願數": NaN,
    "外加名額第一類學群可選填志願數": 21.0,
    "外加名額第二類學群可選填志願數": 9.0,
    "外加名額第三類學群可選填志願數": 1.0,
    "外加名額第四類學群可選填志願數": NaN,
    "外加名額第五類學群可選填志願數": NaN,
    "外加名額第六類學群可選填志願數": NaN,
    "外加名額第七類學群可選填志願數": NaN,
    "外加名額第八類學群可選填志願數": NaN
  },
  {
    "代碼": 35,
    "學校名稱": "臺北市立大學",
    "址址": "臺北市中正區愛國西路1號",
    "郵遞區號": 100234,
    "學校簡稱": "北市大",
    "學業成績百分比": 50,
    "不分學群可選填志願數": NaN,
    "一類學群可選填志願數": 12.0,
    "二類學群可選填志願數": 7.0,
    "三類學群可選填志願數": 1.0,
    "四類學群可選填志願數": NaN,
    "五類學群可選填志願數": NaN,
    "六類學群可選填志願數": NaN,
    "七類學群可選填志願數": NaN,
    "八類學群可選填志願數": NaN,
    "外加名額不分學群可選填志願數": NaN,
    "外加名額第一類學群可選填志願數": 9.0,
    "外加名額第二類學群可選填志願數": 7.0,
    "外加名額第三類學群可選填志願數": 1.0,
    "外加名額第四類學群可選填志願數": NaN,
    "外加名額第五類學群可選填志願數": NaN,
    "外加名額第六類學群可選填志願數": NaN,
    "外加名額第七類學群可選填志願數": NaN,
    "外加名額第八類學群可選填志願數": NaN
  },
  {
    "代碼": 36,
    "學校名稱": "國立屏東大學",
    "址址": "屏東市民生路4-18號",
    "郵遞區號": 900391,
    "學校簡稱": "屏東大",
    "學業成績百分比": 40,
    "不分學群可選填志願數": NaN,
    "一類學群可選填志願數": 9.0,
    "二類學群可選填志願數": 5.0,
    "三類學群可選填志願數": NaN,
    "四類學群可選填志願數": NaN,
    "五類學群可選填志願數": 1.0,
    "六類學群可選填志願數": NaN,
    "七類學群可選填志願數": NaN,
    "八類學群可選填志願數": NaN,
    "外加名額不分學群可選填志願數": NaN,
    "外加名額第一類學群可選填志願數": 9.0,
    "外加名額第二類學群可選填志願數": 4.0,
    "外加名額第三類學群可選填志願數": NaN,
    "外加名額第四類學群可選填志願數": NaN,
    "外加名額第五類學群可選填志願數": 1.0,
    "外加名額第六類學群可選填志願數": NaN,
    "外加名額第七類學群可選填志願數": NaN,
    "外加名額第八類學群可選填志願數": NaN
  },
  {
    "代碼": 38,
    "學校名稱": "國立臺東大學",
    "址址": "臺東市大學路二段369號",
    "郵遞區號": 95092,
    "學校簡稱": "東大",
    "學業成績百分比": 50,
    "不分學群可選填志願數": NaN,
    "一類學群可選填志願數": 9.0,
    "二類學群可選填志願數": 6.0,
    "三類學群可選填志願數": 2.0,
    "四類學群可選填志願數": NaN,
    "五類學群可選填志願數": 1.0,
    "六類學群可選填志願數": NaN,
    "七類學群可選填志願數": 1.0,
    "八類學群可選填志願數": NaN,
    "外加名額不分學群可選填志願數": NaN,
    "外加名額第一類學群可選填志願數": 7.0,
    "外加名額第二類學群可選填志願數": 6.0,
    "外加名額第三類學群可選填志願數": 1.0,
    "外加名額第四類學群可選填志願數": NaN,
    "外加名額第五類學群可選填志願數": NaN,
    "外加名額第六類學群可選填志願數": NaN,
    "外加名額第七類學群可選填志願數": NaN,
    "外加名額第八類學群可選填志願數": NaN
  },
  {
    "代碼": 39,
    "學校名稱": "國立體育大學",
    "址址": "桃園市龜山區文化一路250號",
    "郵遞區號": 333325,
    "學校簡稱": "國體大",
    "學業成績百分比": 50,
    "不分學群可選填志願數": NaN,
    "一類學群可選填志願數": 2.0,
    "二類學群可選填志願數": NaN,
    "三類學群可選填志願數": 1.0,
    "四類學群可選填志願數": NaN,
    "五類學群可選填志願數": NaN,
    "六類學群可選填志願數": NaN,
    "七類學群可選填志願數": NaN,
    "八類學群可選填志願數": NaN,
    "外加名額不分學群可選填志願數": NaN,
    "外加名額第一類學群可選填志願數": 2.0,
    "外加名額第二類學群可選填志願數": NaN,
    "外加名額第三類學群可選填志願數": 1.0,
    "外加名額第四類學群可選填志願數": NaN,
    "外加名額第五類學群可選填志願數": NaN,
    "外加名額第六類學群可選填志願數": NaN,
    "外加名額第七類學群可選填志願數": NaN,
    "外加名額第八類學群可選填志願數": NaN
  },
  {
    "代碼": 40,
    "學校名稱": "元智大學",
    "址址": "桃園市中壢區遠東路135號",
    "郵遞區號": 320315,
    "學校簡稱": "元智",
    "學業成績百分比": 50,
    "不分學群可選填志願數": NaN,
    "一類學群可選填志願數": 13.0,
    "二類學群可選填志願數": 10.0,
    "三類學群可選填志願數": 1.0,
    "四類學群可選填志願數": NaN,
    "五類學群可選填志願數": NaN,
    "六類學群可選填志願數": NaN,
    "七類學群可選填志願數": NaN,
    "八類學群可選填志願數": NaN,
    "外加名額不分學群可選填志願數": NaN,
    "外加名額第一類學群可選填志願數": 11.0,
    "外加名額第二類學群可選填志願數": 10.0,
    "外加名額第三類學群可選填志願數": 1.0,
    "外加名額第四類學群可選填志願數": NaN,
    "外加名額第五類學群可選填志願數": NaN,
    "外加名額第六類學群可選填志願數": NaN,
    "外加名額第七類學群可選填志願數": NaN,
    "外加名額第八類學群可選填志願數": NaN
  },
  {
    "代碼": 41,
    "學校名稱": "國立中正大學",
    "址址": "嘉義縣民雄鄉大學路一段168號",
    "郵遞區號": 621301,
    "學校簡稱": "中正",
    "學業成績百分比": 30,
    "不分學群可選填志願數": NaN,
    "一類學群可選填志願數": 17.0,
    "二類學群可選填志願數": 11.0,
    "三類學群可選填志願數": 2.0,
    "四類學群可選填志願數": NaN,
    "五類學群可選填志願數": NaN,
    "六類學群可選填志願數": NaN,
    "七類學群可選填志願數": 1.0,
    "八類學群可選填志願數": NaN,
    "外加名額不分學群可選填志願數": NaN,
    "外加名額第一類學群可選填志願數": 12.0,
    "外加名額第二類學群可選填志願數": 3.0,
    "外加名額第三類學群可選填志願數": 2.0,
    "外加名額第四類學群可選填志願數": NaN,
    "外加名額第五類學群可選填志願數": NaN,
    "外加名額第六類學群可選填志願數": NaN,
    "外加名額第七類學群可選填志願數": 1.0,
    "外加名額第八類學群可選填志願數": NaN
  },
  {
    "代碼": 42,
    "學校名稱": "大葉大學",
    "址址": "彰化縣大村鄉學府路168號",
    "郵遞區號": 51591,
    "學校簡稱": "大葉",
    "學業成績百分比": 50,
    "不分學群可選填志願數": NaN,
    "一類學群可選填志願數": 7.0,
    "二類學群可選填志願數": 9.0,
    "三類學群可選填志願數": 5.0,
    "四類學群可選填志願數": NaN,
    "五類學群可選填志願數": NaN,
    "六類學群可選填志願數": NaN,
    "七類學群可選填志願數": NaN,
    "八類學群可選填志願數": NaN,
    "外加名額不分學群可選填志願數": NaN,
    "外加名額第一類學群可選填志願數": 6.0,
    "外加名額第二類學群可選填志願數": 6.0,
    "外加名額第三類學群可選填志願數": 5.0,
    "外加名額第四類學群可選填志願數": NaN,
    "外加名額第五類學群可選填志願數": NaN,
    "外加名額第六類學群可選填志願數": NaN,
    "外加名額第七類學群可選填志願數": NaN,
    "外加名額第八類學群可選填志願數": NaN
  },
  {
    "代碼": 44,
    "學校名稱": "華梵大學",
    "址址": "新北市石碇區華梵路1號",
    "郵遞區號": 22301,
    "學校簡稱": "華梵",
    "學業成績百分比": 50,
    "不分學群可選填志願數": NaN,
    "一類學群可選填志願數": 6.0,
    "二類學群可選填志願數": 1.0,
    "三類學群可選填志願數": NaN,
    "四類學群可選填志願數": NaN,
    "五類學群可選填志願數": 1.0,
    "六類學群可選填志願數": NaN,
    "七類學群可選填志願數": NaN,
    "八類學群可選填志願數": NaN,
    "外加名額不分學群可選填志願數": NaN,
    "外加名額第一類學群可選填志願數": 3.0,
    "外加名額第二類學群可選填志願數": 1.0,
    "外加名額第三類學群可選填志願數": NaN,
    "外加名額第四類學群可選填志願數": NaN,
    "外加名額第五類學群可選填志願數": 1.0,
    "外加名額第六類學群可選填志願數": NaN,
    "外加名額第七類學群可選填志願數": NaN,
    "外加名額第八類學群可選填志願數": NaN
  },
  {
    "代碼": 45,
    "學校名稱": "義守大學",
    "址址": "高雄市大樹區學城路一段1號",
    "郵遞區號": 84001,
    "學校簡稱": "義守",
    "學業成績百分比": 50,
    "不分學群可選填志願數": NaN,
    "一類學群可選填志願數": 12.0,
    "二類學群可選填志願數": 9.0,
    "三類學群可選填志願數": 8.0,
    "四類學群可選填志願數": NaN,
    "五類學群可選填志願數": NaN,
    "六類學群可選填志願數": NaN,
    "七類學群可選填志願數": NaN,
    "八類學群可選填志願數": NaN,
    "外加名額不分學群可選填志願數": NaN,
    "外加名額第一類學群可選填志願數": 11.0,
    "外加名額第二類學群可選填志願數": 8.0,
    "外加名額第三類學群可選填志願數": 8.0,
    "外加名額第四類學群可選填志願數": NaN,
    "外加名額第五類學群可選填志願數": NaN,
    "外加名額第六類學群可選填志願數": NaN,
    "外加名額第七類學群可選填志願數": NaN,
    "外加名額第八類學群可選填志願數": NaN
  },
  {
    "代碼": 46,
    "學校名稱": "銘傳大學",
    "址址": "臺北市士林區中山北路五段250號",
    "郵遞區號": 11103,
    "學校簡稱": "銘傳",
    "學業成績百分比": 50,
    "不分學群可選填志願數": NaN,
    "一類學群可選填志願數": 38.0,
    "二類學群可選填志願數": 12.0,
    "三類學群可選填志願數": NaN,
    "四類學群可選填志願數": NaN,
    "五類學群可選填志願數": NaN,
    "六類學群可選填志願數": NaN,
    "七類學群可選填志願數": NaN,
    "八類學群可選填志願數": NaN,
    "外加名額不分學群可選填志願數": NaN,
    "外加名額第一類學群可選填志願數": 35.0,
    "外加名額第二類學群可選填志願數": 10.0,
    "外加名額第三類學群可選填志願數": NaN,
    "外加名額第四類學群可選填志願數": NaN,
    "外加名額第五類學群可選填志願數": NaN,
    "外加名額第六類學群可選填志願數": NaN,
    "外加名額第七類學群可選填志願數": NaN,
    "外加名額第八類學群可選填志願數": NaN
  },
  {
    "代碼": 47,
    "學校名稱": "世新大學",
    "址址": "臺北市文山區木柵路一段17巷1號",
    "郵遞區號": 116,
    "學校簡稱": "世新",
    "學業成績百分比": 50,
    "不分學群可選填志願數": NaN,
    "一類學群可選填志願數": 22.0,
    "二類學群可選填志願數": NaN,
    "三類學群可選填志願數": NaN,
    "四類學群可選填志願數": NaN,
    "五類學群可選填志願數": NaN,
    "六類學群可選填志願數": NaN,
    "七類學群可選填志願數": NaN,
    "八類學群可選填志願數": NaN,
    "外加名額不分學群可選填志願數": NaN,
    "外加名額第一類學群可選填志願數": 22.0,
    "外加名額第二類學群可選填志願數": NaN,
    "外加名額第三類學群可選填志願數": NaN,
    "外加名額第四類學群可選填志願數": NaN,
    "外加名額第五類學群可選填志願數": NaN,
    "外加名額第六類學群可選填志願數": NaN,
    "外加名額第七類學群可選填志願數": NaN,
    "外加名額第八類學群可選填志願數": NaN
  },
  {
    "代碼": 50,
    "學校名稱": "實踐大學",
    "址址": "臺北市中山區大直街70號",
    "郵遞區號": 104336,
    "學校簡稱": "實踐",
    "學業成績百分比": 50,
    "不分學群可選填志願數": NaN,
    "一類學群可選填志願數": 32.0,
    "二類學群可選填志願數": 12.0,
    "三類學群可選填志願數": 2.0,
    "四類學群可選填志願數": NaN,
    "五類學群可選填志願數": 3.0,
    "六類學群可選填志願數": NaN,
    "七類學群可選填志願數": 2.0,
    "八類學群可選填志願數": NaN,
    "外加名額不分學群可選填志願數": NaN,
    "外加名額第一類學群可選填志願數": 28.0,
    "外加名額第二類學群可選填志願數": 8.0,
    "外加名額第三類學群可選填志願數": 2.0,
    "外加名額第四類學群可選填志願數": NaN,
    "外加名額第五類學群可選填志願數": NaN,
    "外加名額第六類學群可選填志願數": NaN,
    "外加名額第七類學群可選填志願數": 2.0,
    "外加名額第八類學群可選填志願數": NaN
  },
  {
    "代碼": 51,
    "學校名稱": "長榮大學",
    "址址": "臺南市歸仁區長大路1號",
    "郵遞區號": 711301,
    "學校簡稱": "長榮",
    "學業成績百分比": 50,
    "不分學群可選填志願數": NaN,
    "一類學群可選填志願數": 10.0,
    "二類學群可選填志願數": 4.0,
    "三類學群可選填志願數": 3.0,
    "四類學群可選填志願數": NaN,
    "五類學群可選填志願數": 1.0,
    "六類學群可選填志願數": NaN,
    "七類學群可選填志願數": NaN,
    "八類學群可選填志願數": NaN,
    "外加名額不分學群可選填志願數": NaN,
    "外加名額第一類學群可選填志願數": 10.0,
    "外加名額第二類學群可選填志願數": 4.0,
    "外加名額第三類學群可選填志願數": 3.0,
    "外加名額第四類學群可選填志願數": NaN,
    "外加名額第五類學群可選填志願數": 1.0,
    "外加名額第六類學群可選填志願數": NaN,
    "外加名額第七類學群可選填志願數": NaN,
    "外加名額第八類學群可選填志願數": NaN
  },
  {
    "代碼": 56,
    "學校名稱": "國立臺灣藝術大學",
    "址址": "新北市板橋區大觀路一段59號",
    "郵遞區號": 22058,
    "學校簡稱": "臺藝大",
    "學業成績百分比": 30,
    "不分學群可選填志願數": NaN,
    "一類學群可選填志願數": 4.0,
    "二類學群可選填志願數": NaN,
    "三類學群可選填志願數": NaN,
    "四類學群可選填志願數": 1.0,
    "五類學群可選填志願數": 7.0,
    "六類學群可選填志願數": NaN,
    "七類學群可選填志願數": NaN,
    "八類學群可選填志願數": NaN,
    "外加名額不分學群可選填志願數": NaN,
    "外加名額第一類學群可選填志願數": 4.0,
    "外加名額第二類學群可選填志願數": NaN,
    "外加名額第三類學群可選填志願數": NaN,
    "外加名額第四類學群可選填志願數": 1.0,
    "外加名額第五類學群可選填志願數": 3.0,
    "外加名額第六類學群可選填志願數": NaN,
    "外加名額第七類學群可選填志願數": NaN,
    "外加名額第八類學群可選填志願數": NaN
  },
  {
    "代碼": 58,
    "學校名稱": "國立暨南國際大學",
    "址址": "南投縣埔里鎮大學路1號",
    "郵遞區號": 545301,
    "學校簡稱": "暨南",
    "學業成績百分比": 50,
    "不分學群可選填志願數": NaN,
    "一類學群可選填志願數": 19.0,
    "二類學群可選填志願數": 6.0,
    "三類學群可選填志願數": 1.0,
    "四類學群可選填志願數": NaN,
    "五類學群可選填志願數": NaN,
    "六類學群可選填志願數": NaN,
    "七類學群可選填志願數": NaN,
    "八類學群可選填志願數": NaN,
    "外加名額不分學群可選填志願數": NaN,
    "外加名額第一類學群可選填志願數": 7.0,
    "外加名額第二類學群可選填志願數": 2.0,
    "外加名額第三類學群可選填志願數": 1.0,
    "外加名額第四類學群可選填志願數": NaN,
    "外加名額第五類學群可選填志願數": NaN,
    "外加名額第六類學群可選填志願數": NaN,
    "外加名額第七類學群可選填志願數": NaN,
    "外加名額第八類學群可選填志願數": NaN
  },
  {
    "代碼": 59,
    "學校名稱": "南華大學",
    "址址": "嘉義縣大林鎮南華路一段55號",
    "郵遞區號": 622301,
    "學校簡稱": "南華",
    "學業成績百分比": 50,
    "不分學群可選填志願數": NaN,
    "一類學群可選填志願數": 21.0,
    "二類學群可選填志願數": 8.0,
    "三類學群可選填志願數": 1.0,
    "四類學群可選填志願數": NaN,
    "五類學群可選填志願數": NaN,
    "六類學群可選填志願數": NaN,
    "七類學群可選填志願數": NaN,
    "八類學群可選填志願數": NaN,
    "外加名額不分學群可選填志願數": NaN,
    "外加名額第一類學群可選填志願數": 18.0,
    "外加名額第二類學群可選填志願數": 7.0,
    "外加名額第三類學群可選填志願數": NaN,
    "外加名額第四類學群可選填志願數": NaN,
    "外加名額第五類學群可選填志願數": NaN,
    "外加名額第六類學群可選填志願數": NaN,
    "外加名額第七類學群可選填志願數": NaN,
    "外加名額第八類學群可選填志願數": NaN
  },
  {
    "代碼": 60,
    "學校名稱": "國立臺灣體育運動大學",
    "址址": "臺中市北區雙十路一段16號",
    "郵遞區號": 40404,
    "學校簡稱": "臺體大",
    "學業成績百分比": 50,
    "不分學群可選填志願數": NaN,
    "一類學群可選填志願數": 2.0,
    "二類學群可選填志願數": NaN,
    "三類學群可選填志願數": 1.0,
    "四類學群可選填志願數": NaN,
    "五類學群可選填志願數": NaN,
    "六類學群可選填志願數": NaN,
    "七類學群可選填志願數": NaN,
    "八類學群可選填志願數": NaN,
    "外加名額不分學群可選填志願數": NaN,
    "外加名額第一類學群可選填志願數": 2.0,
    "外加名額第二類學群可選填志願數": NaN,
    "外加名額第三類學群可選填志願數": 1.0,
    "外加名額第四類學群可選填志願數": NaN,
    "外加名額第五類學群可選填志願數": NaN,
    "外加名額第六類學群可選填志願數": NaN,
    "外加名額第七類學群可選填志願數": NaN,
    "外加名額第八類學群可選填志願數": NaN
  },
  {
    "代碼": 63,
    "學校名稱": "國立臺南藝術大學",
    "址址": "臺南市官田區大崎里大崎66號",
    "郵遞區號": 720005,
    "學校簡稱": "南藝大",
    "學業成績百分比": 40,
    "不分學群可選填志願數": NaN,
    "一類學群可選填志願數": 2.0,
    "二類學群可選填志願數": NaN,
    "三類學群可選填志願數": NaN,
    "四類學群可選填志願數": NaN,
    "五類學群可選填志願數": 1.0,
    "六類學群可選填志願數": NaN,
    "七類學群可選填志願數": NaN,
    "八類學群可選填志願數": NaN,
    "外加名額不分學群可選填志願數": NaN,
    "外加名額第一類學群可選填志願數": 2.0,
    "外加名額第二類學群可選填志願數": NaN,
    "外加名額第三類學群可選填志願數": NaN,
    "外加名額第四類學群可選填志願數": NaN,
    "外加名額第五類學群可選填志願數": 1.0,
    "外加名額第六類學群可選填志願數": NaN,
    "外加名額第七類學群可選填志願數": NaN,
    "外加名額第八類學群可選填志願數": NaN
  },
  {
    "代碼": 65,
    "學校名稱": "玄奘大學",
    "址址": "新竹市香山區玄奘路48號",
    "郵遞區號": 30092,
    "學校簡稱": "玄奘",
    "學業成績百分比": 50,
    "不分學群可選填志願數": NaN,
    "一類學群可選填志願數": 6.0,
    "二類學群可選填志願數": NaN,
    "三類學群可選填志願數": NaN,
    "四類學群可選填志願數": NaN,
    "五類學群可選填志願數": NaN,
    "六類學群可選填志願數": NaN,
    "七類學群可選填志願數": NaN,
    "八類學群可選填志願數": NaN,
    "外加名額不分學群可選填志願數": NaN,
    "外加名額第一類學群可選填志願數": 4.0,
    "外加名額第二類學群可選填志願數": NaN,
    "外加名額第三類學群可選填志願數": NaN,
    "外加名額第四類學群可選填志願數": NaN,
    "外加名額第五類學群可選填志願數": NaN,
    "外加名額第六類學群可選填志願數": NaN,
    "外加名額第七類學群可選填志願數": NaN,
    "外加名額第八類學群可選填志願數": NaN
  },
  {
    "代碼": 79,
    "學校名稱": "真理大學",
    "址址": "新北市淡水區真理街32號",
    "郵遞區號": 251,
    "學校簡稱": "真理",
    "學業成績百分比": 50,
    "不分學群可選填志願數": NaN,
    "一類學群可選填志願數": 11.0,
    "二類學群可選填志願數": 1.0,
    "三類學群可選填志願數": NaN,
    "四類學群可選填志願數": 2.0,
    "五類學群可選填志願數": NaN,
    "六類學群可選填志願數": NaN,
    "七類學群可選填志願數": 2.0,
    "八類學群可選填志願數": NaN,
    "外加名額不分學群可選填志願數": NaN,
    "外加名額第一類學群可選填志願數": 7.0,
    "外加名額第二類學群可選填志願數": NaN,
    "外加名額第三類學群可選填志願數": NaN,
    "外加名額第四類學群可選填志願數": 1.0,
    "外加名額第五類學群可選填志願數": NaN,
    "外加名額第六類學群可選填志願數": NaN,
    "外加名額第七類學群可選填志願數": 1.0,
    "外加名額第八類學群可選填志願數": NaN
  },
  {
    "代碼": 99,
    "學校名稱": "國立臺北大學",
    "址址": "新北市三峽區大學路151號",
    "郵遞區號": 237303,
    "學校簡稱": "北大",
    "學業成績百分比": 20,
    "不分學群可選填志願數": NaN,
    "一類學群可選填志願數": 17.0,
    "二類學群可選填志願數": 3.0,
    "三類學群可選填志願數": NaN,
    "四類學群可選填志願數": NaN,
    "五類學群可選填志願數": NaN,
    "六類學群可選填志願數": NaN,
    "七類學群可選填志願數": NaN,
    "八類學群可選填志願數": NaN,
    "外加名額不分學群可選填志願數": NaN,
    "外加名額第一類學群可選填志願數": 10.0,
    "外加名額第二類學群可選填志願數": NaN,
    "外加名額第三類學群可選填志願數": NaN,
    "外加名額第四類學群可選填志願數": NaN,
    "外加名額第五類學群可選填志願數": NaN,
    "外加名額第六類學群可選填志願數": NaN,
    "外加名額第七類學群可選填志願數": NaN,
    "外加名額第八類學群可選填志願數": NaN
  },
  {
    "代碼": 100,
    "學校名稱": "國立嘉義大學",
    "址址": "嘉義市學府路300號",
    "郵遞區號": 600355,
    "學校簡稱": "嘉大",
    "學業成績百分比": 30,
    "不分學群可選填志願數": NaN,
    "一類學群可選填志願數": 7.0,
    "二類學群可選填志願數": 5.0,
    "三類學群可選填志願數": 7.0,
    "四類學群可選填志願數": NaN,
    "五類學群可選填志願數": 1.0,
    "六類學群可選填志願數": NaN,
    "七類學群可選填志願數": NaN,
    "八類學群可選填志願數": NaN,
    "外加名額不分學群可選填志願數": NaN,
    "外加名額第一類學群可選填志願數": 7.0,
    "外加名額第二類學群可選填志願數": 4.0,
    "外加名額第三類學群可選填志願數": 7.0,
    "外加名額第四類學群可選填志願數": NaN,
    "外加名額第五類學群可選填志願數": 1.0,
    "外加名額第六類學群可選填志願數": NaN,
    "外加名額第七類學群可選填志願數": NaN,
    "外加名額第八類學群可選填志願數": NaN
  },
  {
    "代碼": 101,
    "學校名稱": "國立高雄大學",
    "址址": "高雄市楠梓區高雄大學路700號",
    "郵遞區號": 81148,
    "學校簡稱": "高大",
    "學業成績百分比": 30,
    "不分學群可選填志願數": NaN,
    "一類學群可選填志願數": 13.0,
    "二類學群可選填志願數": 10.0,
    "三類學群可選填志願數": 1.0,
    "四類學群可選填志願數": NaN,
    "五類學群可選填志願數": NaN,
    "六類學群可選填志願數": NaN,
    "七類學群可選填志願數": NaN,
    "八類學群可選填志願數": NaN,
    "外加名額不分學群可選填志願數": NaN,
    "外加名額第一類學群可選填志願數": 8.0,
    "外加名額第二類學群可選填志願數": 6.0,
    "外加名額第三類學群可選填志願數": 1.0,
    "外加名額第四類學群可選填志願數": NaN,
    "外加名額第五類學群可選填志願數": NaN,
    "外加名額第六類學群可選填志願數": NaN,
    "外加名額第七類學群可選填志願數": NaN,
    "外加名額第八類學群可選填志願數": NaN
  },
  {
    "代碼": 108,
    "學校名稱": "慈濟大學",
    "址址": "花蓮縣花蓮市中央路三段701號",
    "郵遞區號": 970374,
    "學校簡稱": "慈濟",
    "學業成績百分比": 50,
    "不分學群可選填志願數": NaN,
    "一類學群可選填志願數": 6.0,
    "二類學群可選填志願數": 3.0,
    "三類學群可選填志願數": 7.0,
    "四類學群可選填志願數": NaN,
    "五類學群可選填志願數": NaN,
    "六類學群可選填志願數": NaN,
    "七類學群可選填志願數": NaN,
    "八類學群可選填志願數": 1.0,
    "外加名額不分學群可選填志願數": NaN,
    "外加名額第一類學群可選填志願數": 2.0,
    "外加名額第二類學群可選填志願數": 2.0,
    "外加名額第三類學群可選填志願數": 6.0,
    "外加名額第四類學群可選填志願數": NaN,
    "外加名額第五類學群可選填志願數": NaN,
    "外加名額第六類學群可選填志願數": NaN,
    "外加名額第七類學群可選填志願數": NaN,
    "外加名額第八類學群可選填志願數": NaN
  },
  {
    "代碼": 109,
    "學校名稱": "臺北醫學大學",
    "址址": "臺北市信義區吳興街250號",
    "郵遞區號": 110301,
    "學校簡稱": "北醫",
    "學業成績百分比": 40,
    "不分學群可選填志願數": NaN,
    "一類學群可選填志願數": 1.0,
    "二類學群可選填志願數": NaN,
    "三類學群可選填志願數": 7.0,
    "四類學群可選填志願數": NaN,
    "五類學群可選填志願數": NaN,
    "六類學群可選填志願數": NaN,
    "七類學群可選填志願數": NaN,
    "八類學群可選填志願數": 2.0,
    "外加名額不分學群可選填志願數": NaN,
    "外加名額第一類學群可選填志願數": 1.0,
    "外加名額第二類學群可選填志願數": NaN,
    "外加名額第三類學群可選填志願數": 8.0,
    "外加名額第四類學群可選填志願數": NaN,
    "外加名額第五類學群可選填志願數": NaN,
    "外加名額第六類學群可選填志願數": NaN,
    "外加名額第七類學群可選填志願數": NaN,
    "外加名額第八類學群可選填志願數": 1.0
  },
  {
    "代碼": 110,
    "學校名稱": "開南大學",
    "址址": "桃園市蘆竹區開南路1號",
    "郵遞區號": 338103,
    "學校簡稱": "開南",
    "學業成績百分比": 50,
    "不分學群可選填志願數": NaN,
    "一類學群可選填志願數": 14.0,
    "二類學群可選填志願數": 1.0,
    "三類學群可選填志願數": 1.0,
    "四類學群可選填志願數": NaN,
    "五類學群可選填志願數": NaN,
    "六類學群可選填志願數": NaN,
    "七類學群可選填志願數": NaN,
    "八類學群可選填志願數": NaN,
    "外加名額不分學群可選填志願數": NaN,
    "外加名額第一類學群可選填志願數": 14.0,
    "外加名額第二類學群可選填志願數": 1.0,
    "外加名額第三類學群可選填志願數": 1.0,
    "外加名額第四類學群可選填志願數": NaN,
    "外加名額第五類學群可選填志願數": NaN,
    "外加名額第六類學群可選填志願數": NaN,
    "外加名額第七類學群可選填志願數": NaN,
    "外加名額第八類學群可選填志願數": NaN
  },
  {
    "代碼": 112,
    "學校名稱": "康寧大學",
    "址址": "臺北市內湖區康寧路三段75巷137號",
    "郵遞區號": 114,
    "學校簡稱": "康寧",
    "學業成績百分比": 50,
    "不分學群可選填志願數": NaN,
    "一類學群可選填志願數": 2.0,
    "二類學群可選填志願數": NaN,
    "三類學群可選填志願數": NaN,
    "四類學群可選填志願數": NaN,
    "五類學群可選填志願數": NaN,
    "六類學群可選填志願數": NaN,
    "七類學群可選填志願數": NaN,
    "八類學群可選填志願數": NaN,
    "外加名額不分學群可選填志願數": NaN,
    "外加名額第一類學群可選填志願數": 1.0,
    "外加名額第二類學群可選填志願數": NaN,
    "外加名額第三類學群可選填志願數": NaN,
    "外加名額第四類學群可選填志願數": NaN,
    "外加名額第五類學群可選填志願數": NaN,
    "外加名額第六類學群可選填志願數": NaN,
    "外加名額第七類學群可選填志願數": NaN,
    "外加名額第八類學群可選填志願數": NaN
  },
  {
    "代碼": 113,
    "學校名稱": "中信金融管理學院",
    "址址": "臺南市安南區台江大道三段600號",
    "郵遞區號": 709,
    "學校簡稱": "中金院",
    "學業成績百分比": 50,
    "不分學群可選填志願數": NaN,
    "一類學群可選填志願數": 3.0,
    "二類學群可選填志願數": NaN,
    "三類學群可選填志願數": NaN,
    "四類學群可選填志願數": NaN,
    "五類學群可選填志願數": NaN,
    "六類學群可選填志願數": NaN,
    "七類學群可選填志願數": NaN,
    "八類學群可選填志願數": NaN,
    "外加名額不分學群可選填志願數": NaN,
    "外加名額第一類學群可選填志願數": 3.0,
    "外加名額第二類學群可選填志願數": NaN,
    "外加名額第三類學群可選填志願數": NaN,
    "外加名額第四類學群可選填志願數": NaN,
    "外加名額第五類學群可選填志願數": NaN,
    "外加名額第六類學群可選填志願數": NaN,
    "外加名額第七類學群可選填志願數": NaN,
    "外加名額第八類學群可選填志願數": NaN
  },
  {
    "代碼": 130,
    "學校名稱": "佛光大學",
    "址址": "宜蘭縣礁溪鄉林美村林尾路160號",
    "郵遞區號": 262,
    "學校簡稱": "佛光",
    "學業成績百分比": 50,
    "不分學群可選填志願數": NaN,
    "一類學群可選填志願數": 9.0,
    "二類學群可選填志願數": 8.0,
    "三類學群可選填志願數": 1.0,
    "四類學群可選填志願數": NaN,
    "五類學群可選填志願數": NaN,
    "六類學群可選填志願數": NaN,
    "七類學群可選填志願數": NaN,
    "八類學群可選填志願數": NaN,
    "外加名額不分學群可選填志願數": NaN,
    "外加名額第一類學群可選填志願數": 1.0,
    "外加名額第二類學群可選填志願數": NaN,
    "外加名額第三類學群可選填志願數": NaN,
    "外加名額第四類學群可選填志願數": NaN,
    "外加名額第五類學群可選填志願數": NaN,
    "外加名額第六類學群可選填志願數": NaN,
    "外加名額第七類學群可選填志願數": NaN,
    "外加名額第八類學群可選填志願數": NaN
  },
  {
    "代碼": 134,
    "學校名稱": "亞洲大學",
    "址址": "臺中市霧峰區柳豐路500號",
    "郵遞區號": 41354,
    "學校簡稱": "亞洲",
    "學業成績百分比": 50,
    "不分學群可選填志願數": NaN,
    "一類學群可選填志願數": 16.0,
    "二類學群可選填志願數": 5.0,
    "三類學群可選填志願數": 15.0,
    "四類學群可選填志願數": NaN,
    "五類學群可選填志願數": NaN,
    "六類學群可選填志願數": NaN,
    "七類學群可選填志願數": NaN,
    "八類學群可選填志願數": NaN,
    "外加名額不分學群可選填志願數": NaN,
    "外加名額第一類學群可選填志願數": 15.0,
    "外加名額第二類學群可選填志願數": 5.0,
    "外加名額第三類學群可選填志願數": 14.0,
    "外加名額第四類學群可選填志願數": NaN,
    "外加名額第五類學群可選填志願數": NaN,
    "外加名額第六類學群可選填志願數": NaN,
    "外加名額第七類學群可選填志願數": NaN,
    "外加名額第八類學群可選填志願數": NaN
  },
  {
    "代碼": 150,
    "學校名稱": "國立宜蘭大學",
    "址址": "宜蘭縣宜蘭市神農路一段1號",
    "郵遞區號": 260007,
    "學校簡稱": "宜蘭",
    "學業成績百分比": 50,
    "不分學群可選填志願數": NaN,
    "一類學群可選填志願數": 3.0,
    "二類學群可選填志願數": 8.0,
    "三類學群可選填志願數": 4.0,
    "四類學群可選填志願數": NaN,
    "五類學群可選填志願數": NaN,
    "六類學群可選填志願數": NaN,
    "七類學群可選填志願數": NaN,
    "八類學群可選填志願數": NaN,
    "外加名額不分學群可選填志願數": NaN,
    "外加名額第一類學群可選填志願數": 3.0,
    "外加名額第二類學群可選填志願數": 8.0,
    "外加名額第三類學群可選填志願數": 4.0,
    "外加名額第四類學群可選填志願數": NaN,
    "外加名額第五類學群可選填志願數": NaN,
    "外加名額第六類學群可選填志願數": NaN,
    "外加名額第七類學群可選填志願數": NaN,
    "外加名額第八類學群可選填志願數": NaN
  },
  {
    "代碼": 151,
    "學校名稱": "國立聯合大學",
    "址址": "苗栗市南勢里聯大2號",
    "郵遞區號": 360302,
    "學校簡稱": "聯合",
    "學業成績百分比": 50,
    "不分學群可選填志願數": NaN,
    "一類學群可選填志願數": 8.0,
    "二類學群可選填志願數": 12.0,
    "三類學群可選填志願數": NaN,
    "四類學群可選填志願數": NaN,
    "五類學群可選填志願數": NaN,
    "六類學群可選填志願數": NaN,
    "七類學群可選填志願數": NaN,
    "八類學群可選填志願數": NaN,
    "外加名額不分學群可選填志願數": NaN,
    "外加名額第一類學群可選填志願數": 7.0,
    "外加名額第二類學群可選填志願數": 12.0,
    "外加名額第三類學群可選填志願數": NaN,
    "外加名額第四類學群可選填志願數": NaN,
    "外加名額第五類學群可選填志願數": NaN,
    "外加名額第六類學群可選填志願數": NaN,
    "外加名額第七類學群可選填志願數": NaN,
    "外加名額第八類學群可選填志願數": NaN
  },
  {
    "代碼": 152,
    "學校名稱": "馬偕醫學大學",
    "址址": "新北市三芝區中正路3段46號",
    "郵遞區號": 25245,
    "學校簡稱": "馬偕醫大",
    "學業成績百分比": 20,
    "不分學群可選填志願數": NaN,
    "一類學群可選填志願數": NaN,
    "二類學群可選填志願數": NaN,
    "三類學群可選填志願數": 5.0,
    "四類學群可選填志願數": NaN,
    "五類學群可選填志願數": NaN,
    "六類學群可選填志願數": NaN,
    "七類學群可選填志願數": NaN,
    "八類學群可選填志願數": 1.0,
    "外加名額不分學群可選填志願數": NaN,
    "外加名額第一類學群可選填志願數": NaN,
    "外加名額第二類學群可選填志願數": NaN,
    "外加名額第三類學群可選填志願數": 3.0,
    "外加名額第四類學群可選填志願數": NaN,
    "外加名額第五類學群可選填志願數": NaN,
    "外加名額第六類學群可選填志願數": NaN,
    "外加名額第七類學群可選填志願數": NaN,
    "外加名額第八類學群可選填志願數": 1.0
  },
  {
    "代碼": 153,
    "學校名稱": "國立金門大學",
    "址址": "金門縣金寧鄉大學路1號",
    "郵遞區號": 892009,
    "學校簡稱": "金大",
    "學業成績百分比": 50,
    "不分學群可選填志願數": NaN,
    "一類學群可選填志願數": 11.0,
    "二類學群可選填志願數": 5.0,
    "三類學群可選填志願數": 1.0,
    "四類學群可選填志願數": NaN,
    "五類學群可選填志願數": NaN,
    "六類學群可選填志願數": NaN,
    "七類學群可選填志願數": NaN,
    "八類學群可選填志願數": NaN,
    "外加名額不分學群可選填志願數": NaN,
    "外加名額第一類學群可選填志願數": 11.0,
    "外加名額第二類學群可選填志願數": 5.0,
    "外加名額第三類學群可選填志願數": 1.0,
    "外加名額第四類學群可選填志願數": NaN,
    "外加名額第五類學群可選填志願數": NaN,
    "外加名額第六類學群可選填志願數": NaN,
    "外加名額第七類學群可選填志願數": NaN,
    "外加名額第八類學群可選填志願數": NaN
  }
]